simple_pid/__init__.py
simple_pid/pid.py
simple_pid/pid.pyi
simple_pid/py.typed
simple_pid-2.0.1.dist-info/LICENSE.md
simple_pid-2.0.1.dist-info/METADATA
simple_pid-2.0.1.dist-info/WHEEL
simple_pid-2.0.1.dist-info/top_level.txt
simple_pid-2.0.1.dist-info/RECORD
