Metadata-Version: 2.1
Name: simple-pid
Version: 2.0.1
Summary: A simple, easy to use PID controller
Author: Martin Lundberg
Project-URL: Homepage, https://github.com/m-lundberg/simple-pid
Project-URL: Documentation, https://simple-pid.readthedocs.io/
Keywords: pid,controller,control
Classifier: Development Status :: 5 - Production/Stable
Classifier: Programming Language :: Python :: 3
Classifier: License :: OSI Approved :: MIT License
Classifier: Operating System :: OS Independent
Requires-Python: >=3.6
License-File: LICENSE.md
Provides-Extra: test
Requires-Dist: pytest; extra == "test"
Provides-Extra: doc
Requires-Dist: furo==2023.3.27; extra == "doc"
Requires-Dist: myst-parser==1.0.0; extra == "doc"
Requires-Dist: sphinx==6.2.1; extra == "doc"
Requires-Dist: sphinx-copybutton==0.5.2; extra == "doc"
Provides-Extra: examples
Requires-Dist: numpy; extra == "examples"
Requires-Dist: matplotlib; extra == "examples"
